pa_utils/__init__.py
pa_utils/core.py
pa_utils/corev2.py
pa_utils/pa_annotator.py
pa_utils-0.0.4.dist-info/METADATA
pa_utils-0.0.4.dist-info/WHEEL
pa_utils-0.0.4.dist-info/top_level.txt
pa_utils-0.0.4.dist-info/RECORD
